wagtail_menubuilder/__init__.py
wagtail_menubuilder/admin.py
wagtail_menubuilder/apps.py
wagtail_menubuilder/models.py
wagtail_menubuilder/tests.py
wagtail_menubuilder/views.py
wagtail_menubuilder/migrations/0001_initial.py
wagtail_menubuilder/migrations/0002_menuitem_parent.py
wagtail_menubuilder/migrations/__init__.py
wagtail_menubuilder/static/menubuilder/css/top-navbar.css
wagtail_menubuilder/static/menubuilder/js/top-navbar.js
wagtail_menubuilder/templates/menubuilder/default.html
wagtail_menubuilder/templates/menubuilder/top-navbar.html
wagtail_menubuilder/templatetags/menubuilder_tags.py
wagtail_menubuilder-0.2.1.dist-info/licenses/LICENSE
wagtail_menubuilder-0.2.1.dist-info/METADATA
wagtail_menubuilder-0.2.1.dist-info/WHEEL
wagtail_menubuilder-0.2.1.dist-info/top_level.txt
wagtail_menubuilder-0.2.1.dist-info/RECORD
