Metadata-Version: 2.4
Name: wagtail-menubuilder
Version: 0.2.1
Summary: A flexible menu builder for Wagtail CMS
Home-page: https://github.com/TechBill/wagtail-menubuilder
Author: Bill Fleming
License: MIT
Project-URL: Documentation, https://github.com/TechBill/wagtail-menubuilder
Project-URL: Source, https://github.com/TechBill/wagtail-menubuilder
Project-URL: Tracker, https://github.com/TechBill/wagtail-menubuilder/issues
Classifier: Framework :: Django
Classifier: Framework :: Wagtail
Classifier: Programming Language :: Python :: 3
Requires-Python: >=3.8
License-File: LICENSE
Requires-Dist: wagtail>=6.0
Requires-Dist: Django>=4.2
Dynamic: author
Dynamic: classifier
Dynamic: description
Dynamic: description-content-type
Dynamic: home-page
Dynamic: license
Dynamic: license-file
Dynamic: project-url
Dynamic: requires-dist
Dynamic: requires-python
Dynamic: summary
